headlessagents/__init__.py
headlessagents/_base_client.py
headlessagents/_client.py
headlessagents/_compat.py
headlessagents/_constants.py
headlessagents/_exceptions.py
headlessagents/_files.py
headlessagents/_models.py
headlessagents/_qs.py
headlessagents/_resource.py
headlessagents/_response.py
headlessagents/_streaming.py
headlessagents/_types.py
headlessagents/_version.py
headlessagents/py.typed
headlessagents/_utils/__init__.py
headlessagents/_utils/_logs.py
headlessagents/_utils/_proxy.py
headlessagents/_utils/_reflection.py
headlessagents/_utils/_streams.py
headlessagents/_utils/_sync.py
headlessagents/_utils/_transform.py
headlessagents/_utils/_typing.py
headlessagents/_utils/_utils.py
headlessagents/lib/.keep
headlessagents/resources/__init__.py
headlessagents/types/__init__.py
headlessagents/types/call_agent_response.py
headlessagents/types/check_health_response.py
headlessagents/types/client_call_agent_params.py
headlessagents/types/retrieve_agent_stats_response.py
headlessagents-1.1.2.dist-info/METADATA
headlessagents-1.1.2.dist-info/WHEEL
headlessagents-1.1.2.dist-info/licenses/LICENSE
headlessagents-1.1.2.dist-info/RECORD
